smartlens/__init__.py
smartlens/captions.py
smartlens/documents.py
smartlens/tags.py
smartlens/util.py
smartlens-1.0.0.dist-info/LICENSE
smartlens-1.0.0.dist-info/METADATA
smartlens-1.0.0.dist-info/WHEEL
smartlens-1.0.0.dist-info/top_level.txt
smartlens-1.0.0.dist-info/RECORD
