Metadata-Version: 2.1
Name: smartlens
Version: 1.0.0
Summary: A Python library for the SmartLens API.
Home-page: https://github.com/SmartLens/smartlens-python/
Author: SmartLens Technologies, Inc.
Author-email: michael@smartlens.ai
License: UNKNOWN
Platform: UNKNOWN
Classifier: Programming Language :: Python :: 3
Classifier: License :: OSI Approved :: MIT License
Classifier: Operating System :: OS Independent
Requires-Python: >=3.6
